adapter/__init__.py
adapter/adapter.py
adapter/adapter_server.py
marker_tool/__init__.py
marker_tool/interpreter.py
marker_tool/mymark.py
marker_tool/utils.py
markplus-1.1.dist-info/METADATA
markplus-1.1.dist-info/WHEEL
markplus-1.1.dist-info/entry_points.txt
markplus-1.1.dist-info/top_level.txt
markplus-1.1.dist-info/RECORD
