Metadata-Version: 2.1
Name: markplus
Version: 1.1
Summary: UNKNOWN
Home-page: UNKNOWN
License: UNKNOWN
Platform: UNKNOWN
Requires-Dist: requests (==2.31.0)
